[
	{
		#"slug": "easp",
		"name": "E-Asclepius",
		"image": "etruckingsoft.png",
		"url": "https://github.com/neilbamb/E-asclepius",
		#"date": "Jan 2018",
		"tags": ["Python", "Django", "HTML", "CSS", "JavaScipt", "SQLite", "NLP"]
	},
	{
		"name": "Know Your Neighbourhood",
		"image": "know_ur_neighbor.jpg",
		#"date": "May 2017",
		"description": "An app which detects the severity of a tweet and alerts users with the accuracy of the tweet, whether it authentic or not and its chances of becoming severe in future.",
		"tags": ["Java", "Android", "Python", "Tensorflow", "Deep Learning", "NLP"]
	},
	{
		"name": "Tableau Visualizations",
		"image": "tableau.png",
		"url": "https://public.tableau.com/profile/neilbamb",
		"tags": ["Tableau"]
	},
	{
		"name": "Tennis Match and Betting Prediction",
		"image": "tennis.jpg",
		"url": "https://github.com/neilbamb/",
		"tags": ["Python","Machine Learning"]
	},
	{
		"name": "Sentiment analysis of hotel reviews using Bidirectional Encoder Representations from Transformers (BERT)",
		"image": "Sentiment-Analysis.png",
		"url": "https://github.com/neilbamb/",
		"tags": ["Python", "Pytorch", "Deep Learning"]
	}
]
